AUTHORS.rst
CONTRIBUTING.rst
HISTORY.rst
LICENSE
MANIFEST.in
Makefile
README.rst
TODO.rst
VERSION
pytest.ini
setup.cfg
setup.py
tox.ini
docs/Makefile
docs/authors.rst
docs/conf.py
docs/contributing.rst
docs/history.rst
docs/index.rst
docs/installation.rst
docs/make.bat
docs/readme.rst
docs/requirements.txt
requirements/dev.txt
requirements/install.txt
requirements/setup.txt
requirements/tests.py
src/dask_kafka/__init__.py
src/dask_kafka/scanner.py
src/dask_kafka.egg-info/PKG-INFO
src/dask_kafka.egg-info/SOURCES.txt
src/dask_kafka.egg-info/dependency_links.txt
src/dask_kafka.egg-info/requires.txt
src/dask_kafka.egg-info/top_level.txt
tests/test_package_import.py