Metadata-Version: 1.1
Name: dask-kafka
Version: 0.1.0.dev0
Summary: Dask-Kafka reader
Home-page: https://github.com/rolando/dask-kafka
Author: Rolando (Max) Espinoza
Author-email: rolando@rmax.io
License: MIT
Keywords: dask-kafka
Platform: UNKNOWN
Classifier: Development Status :: 2 - Pre-Alpha
Classifier: Intended Audience :: Developers
Classifier: License :: OSI Approved :: MIT License
Classifier: Natural Language :: English
Classifier: Programming Language :: Python :: 2
Classifier: Programming Language :: Python :: 2.7
Classifier: Programming Language :: Python :: 3
Classifier: Programming Language :: Python :: 3.4
Classifier: Programming Language :: Python :: 3.5
